notemate_files/__init__.py
notemate_files/cli.py
notemate_files-0.1.0.dist-info/METADATA
notemate_files-0.1.0.dist-info/WHEEL
notemate_files-0.1.0.dist-info/entry_points.txt
notemate_files-0.1.0.dist-info/top_level.txt
notemate_files-0.1.0.dist-info/RECORD
