Metadata-Version: 2.1
Name: notemate-files
Version: 0.1.0
Summary: A CLI tool to upload files and directories to your NoteMate cloud.
Home-page: https://github.com/aapka-username/notemate-cli
Author: Abhi
Author-email: abhi@notemate.space
Classifier: Programming Language :: Python :: 3
Classifier: License :: OSI Approved :: MIT License
Classifier: Operating System :: OS Independent
Requires-Python: >=3.6
Requires-Dist: requests>=2.25.0
Requires-Dist: tqdm>=4.60.0
